log/__init__.py
log/__version__.py
log/entry_points.py
log/log.py
log/.ipynb_checkpoints/log-checkpoint.py
villa_logger_jirawutchayapong-0.0.8.dist-info/.ipynb_checkpoints/PKG-INFO-checkpoint
villa_logger_jirawutchayapong-0.0.8.dist-info/.ipynb_checkpoints/SOURCES-checkpoint.txt
villa_logger_jirawutchayapong-0.0.8.dist-info/.ipynb_checkpoints/dependency_links-checkpoint.txt
villa_logger_jirawutchayapong-0.0.8.dist-info/.ipynb_checkpoints/entry_points-checkpoint.txt
villa_logger_jirawutchayapong-0.0.8.dist-info/.ipynb_checkpoints/not-zip-safe-checkpoint
villa_logger_jirawutchayapong-0.0.8.dist-info/.ipynb_checkpoints/requires-checkpoint.txt
villa_logger_jirawutchayapong-0.0.8.dist-info/.ipynb_checkpoints/top_level-checkpoint.txt
villa_logger_jirawutchayapong-0.0.8.dist-info/LICENSE
villa_logger_jirawutchayapong-0.0.8.dist-info/METADATA
villa_logger_jirawutchayapong-0.0.8.dist-info/WHEEL
villa_logger_jirawutchayapong-0.0.8.dist-info/entry_points.txt
villa_logger_jirawutchayapong-0.0.8.dist-info/top_level.txt
villa_logger_jirawutchayapong-0.0.8.dist-info/RECORD
