Metadata-Version: 2.1
Name: villa-logger-jirawutchayapong
Version: 0.0.8
Summary: villa Logger
Home-page: https://github.com/chayapongjirawut/villalogger
Author: Aey Chayapong
Author-email: chayapongjirawut@gmail.com
License: Apache 2.0
Keywords: villa logger template
Platform: UNKNOWN
Classifier: Development Status :: 4 - Beta
Classifier: Intended Audience :: Developers
Classifier: Programming Language :: Python :: 3.8
Requires-Python: >=3.6.*
Requires-Dist: requests
Requires-Dist: boto3
Requires-Dist: awsSchema
Requires-Dist: nicHelper
